pyqb/__init__.py
pyqb-0.2.5.dist-info/LICENSE
pyqb-0.2.5.dist-info/METADATA
pyqb-0.2.5.dist-info/WHEEL
pyqb-0.2.5.dist-info/top_level.txt
pyqb-0.2.5.dist-info/RECORD
