Metadata-Version: 2.1
Name: pyqb
Version: 0.2.5
Summary: Quickbase API Python Wrapper
Home-page: http://github.com/sjmh/pyqb
Author: Steven Hajducko
Author-email: steven_hajducko@intuit.com
License: EPL-1.0
Keywords: quickbase
Platform: UNKNOWN
Classifier: Development Status :: 3 - Alpha
Classifier: Intended Audience :: Developers
Classifier: Environment :: Console
Classifier: Operating System :: POSIX :: Linux
Classifier: Operating System :: MacOS :: MacOS X
Classifier: Topic :: Software Development :: Libraries
Classifier: Programming Language :: Python :: 2
Classifier: Programming Language :: Python :: 2.6
Classifier: Programming Language :: Python :: 2.7
Classifier: Programming Language :: Python :: 3
Requires-Dist: xmltodict
Requires-Dist: requests
Requires-Dist: six
